README.md
setup.py
eevee/__init__.py
eevee.egg-info/PKG-INFO
eevee.egg-info/SOURCES.txt
eevee.egg-info/dependency_links.txt
eevee.egg-info/top_level.txt