Metadata-Version: 1.1
Name: eevee
Version: 0.0.1a0
Summary: Eevee Discord Bot Framework
Home-page: UNKNOWN
Author: Scragly
Author-email: UNKNOWN
License: UNKNOWN
Platform: UNKNOWN
Classifier: Programming Language :: Python :: 3
Classifier: License :: OSI Approved :: MIT License
Classifier: Operating System :: OS Independent
